grokcore.viewlet-4.1-py3.12-nspkg.pth
grokcore/viewlet/__init__.py
grokcore/viewlet/components.py
grokcore/viewlet/configure.zcml
grokcore/viewlet/directive.py
grokcore/viewlet/ftesting.zcml
grokcore/viewlet/interfaces.py
grokcore/viewlet/meta.py
grokcore/viewlet/meta.zcml
grokcore/viewlet/testing.py
grokcore/viewlet/util.py
grokcore/viewlet/tests/__init__.py
grokcore/viewlet/tests/test_base.py
grokcore/viewlet/tests/test_functional.py
grokcore/viewlet/tests/base/__init__.py
grokcore/viewlet/tests/base/viewlet/__init__.py
grokcore/viewlet/tests/base/viewlet/viewlet_ambiguous_manager.py
grokcore/viewlet/tests/base/viewlet/viewlet_references.py
grokcore/viewlet/tests/base/viewlet/viewlet_render_and_template.py
grokcore/viewlet/tests/base/viewlet/viewlet_render_and_template_templates/viewlet.pt
grokcore/viewlet/tests/functional/__init__.py
grokcore/viewlet/tests/functional/viewlet/__init__.py
grokcore/viewlet/tests/functional/viewlet/order.py
grokcore/viewlet/tests/functional/viewlet/template_namespaces.py
grokcore/viewlet/tests/functional/viewlet/view_directive.py
grokcore/viewlet/tests/functional/viewlet/viewlet_available.py
grokcore/viewlet/tests/functional/viewlet/viewlet_context.py
grokcore/viewlet/tests/functional/viewlet/viewlet_context2.py
grokcore/viewlet/tests/functional/viewlet/viewlet_interface.py
grokcore/viewlet/tests/functional/viewlet/viewlet_manager_association.py
grokcore/viewlet/tests/functional/viewlet/viewlet_security.py
grokcore/viewlet/tests/functional/viewlet/viewlet_template.py
grokcore/viewlet/tests/functional/viewlet/viewletmanager_directive.py
grokcore/viewlet/tests/functional/viewlet/viewletmanager_template.py
grokcore/viewlet/tests/functional/viewlet/order_templates/orderview.pt
grokcore/viewlet/tests/functional/viewlet/template_namespaces_templates/index.pt
grokcore/viewlet/tests/functional/viewlet/template_namespaces_templates/mirandaviewlet.pt
grokcore_viewlet-4.1.dist-info/licenses/LICENSE.txt
grokcore_viewlet-4.1.dist-info/METADATA
grokcore_viewlet-4.1.dist-info/WHEEL
grokcore_viewlet-4.1.dist-info/namespace_packages.txt
grokcore_viewlet-4.1.dist-info/top_level.txt
grokcore_viewlet-4.1.dist-info/RECORD
