Metadata-Version: 2.4
Name: grokcore.viewlet
Version: 4.1
Summary: Grok-like configuration for zope viewlets
Home-page: https://github.com/zopefoundation/grokcore.viewlet
Download-URL: https://pypi.org/project/grokcore.viewlet
Author: Grok Team
Author-email: zope-dev@zope.dev
License: ZPL
Classifier: Environment :: Web Environment
Classifier: Intended Audience :: Developers
Classifier: License :: OSI Approved :: Zope Public License
Classifier: Programming Language :: Python
Classifier: Programming Language :: Python :: 3
Classifier: Programming Language :: Python :: 3.9
Classifier: Programming Language :: Python :: 3.10
Classifier: Programming Language :: Python :: 3.11
Classifier: Programming Language :: Python :: 3.12
Classifier: Programming Language :: Python :: 3.13
Classifier: Programming Language :: Python :: Implementation
Classifier: Programming Language :: Python :: Implementation :: CPython
Classifier: Programming Language :: Python :: Implementation :: PyPy
Classifier: Framework :: Zope :: 3
Requires-Python: >=3.9
License-File: LICENSE.txt
Requires-Dist: grokcore.component>=2.5
Requires-Dist: grokcore.security>=1.6
Requires-Dist: grokcore.view>=2.7
Requires-Dist: martian>=0.14
Requires-Dist: setuptools
Requires-Dist: zope.browserpage
Requires-Dist: zope.component
Requires-Dist: zope.contentprovider
Requires-Dist: zope.interface
Requires-Dist: zope.login
Requires-Dist: zope.publisher
Requires-Dist: zope.security
Requires-Dist: zope.viewlet
Provides-Extra: test
Requires-Dist: zope.annotation; extra == "test"
Requires-Dist: zope.app.appsetup; extra == "test"
Requires-Dist: zope.app.publication; extra == "test"
Requires-Dist: zope.app.wsgi[test]; extra == "test"
Requires-Dist: zope.configuration; extra == "test"
Requires-Dist: zope.container; extra == "test"
Requires-Dist: zope.principalregistry; extra == "test"
Requires-Dist: zope.securitypolicy; extra == "test"
Requires-Dist: zope.site; extra == "test"
Requires-Dist: zope.testbrowser; extra == "test"
Requires-Dist: zope.testing; extra == "test"
Requires-Dist: zope.traversing; extra == "test"
Dynamic: author
Dynamic: author-email
Dynamic: classifier
Dynamic: description
Dynamic: download-url
Dynamic: home-page
Dynamic: license
Dynamic: license-file
Dynamic: provides-extra
Dynamic: requires-dist
Dynamic: requires-python
Dynamic: summary
